CHANGES.txt
LICENCE.txt
MANIFEST.in
README.rst
requirements.txt
setup.py
pyutillib/__init__.py
pyutillib/date_utils.py
pyutillib/math_utils.py
pyutillib/string_utils.py
pyutillib/tests.py
pyutillib.egg-info/PKG-INFO
pyutillib.egg-info/SOURCES.txt
pyutillib.egg-info/dependency_links.txt
pyutillib.egg-info/top_level.txt