Metadata-Version: 1.0
Name: pyutillib
Version: 0.1.1
Summary: Small collection of python functions
Home-page: http://github.com/EdwinvO/pyutillib
Author: Edwin van Opstal
Author-email: evo.se-technology.com
License: LICENSE.txt
Platform: UNKNOWN
